judgezoo/__init__.py
judgezoo/_utils.py
judgezoo/adaptive_attacks.py
judgezoo/advprefix.py
judgezoo/aegis_guard.py
judgezoo/base.py
judgezoo/best_of_n.py
judgezoo/config.py
judgezoo/harmbench.py
judgezoo/intention_analysis.py
judgezoo/jail_judge.py
judgezoo/jailbreakbench.py
judgezoo/llama_guard_3.py
judgezoo/llama_guard_4.py
judgezoo/md_judge.py
judgezoo/strong_reject.py
judgezoo/xstest.py
judgezoo-0.1.7.dist-info/METADATA
judgezoo-0.1.7.dist-info/WHEEL
judgezoo-0.1.7.dist-info/top_level.txt
judgezoo-0.1.7.dist-info/RECORD
