Metadata-Version: 2.4
Name: judgezoo
Version: 0.1.7
Summary: A collection of judges for evaluating LLM model output for safety & toxicity with a standardized API.
Author: Tim Beyer
Author-email: Tim Beyer <tim.beyer@tum.de>
Project-URL: Homepage, https://github.com/LLM-QC/judgezoo
Project-URL: Repository, https://github.com/LLM-QC/judgezoo
Project-URL: Issues, https://github.com/LLM-QC/judgezoo/issues
Keywords: llm,safety,evaluation,ai-safety,machine-learning
Classifier: Development Status :: 4 - Beta
Classifier: Intended Audience :: Developers
Classifier: Intended Audience :: Science/Research
Classifier: Operating System :: OS Independent
Classifier: Programming Language :: Python :: 3
Classifier: Programming Language :: Python :: 3.8
Classifier: Programming Language :: Python :: 3.9
Classifier: Programming Language :: Python :: 3.10
Classifier: Programming Language :: Python :: 3.11
Classifier: Programming Language :: Python :: 3.12
Classifier: Topic :: Scientific/Engineering :: Artificial Intelligence
Classifier: Topic :: Security
Classifier: Topic :: Software Development :: Libraries :: Python Modules
Requires-Python: >=3.8
Requires-Dist: torch>=2.3.1
Requires-Dist: transformers>=4.57.0
Requires-Dist: numpy
Requires-Dist: openai
Requires-Dist: anthropic
Requires-Dist: ipykernel
Requires-Dist: peft
Requires-Dist: sentencepiece
Provides-Extra: test
Requires-Dist: pytest; extra == "test"
Requires-Dist: pytest-cov; extra == "test"
Requires-Dist: pytest-mock; extra == "test"
Provides-Extra: dev
Requires-Dist: pytest; extra == "dev"
Requires-Dist: pytest-cov; extra == "dev"
Requires-Dist: pytest-mock; extra == "dev"
Requires-Dist: build; extra == "dev"
Requires-Dist: twine; extra == "dev"
Dynamic: author
